minchin/pelican/plugins/summary/__init__.py
minchin/pelican/plugins/summary/summary.py
minchin/pelican/plugins/summary/test_summary.py
minchin_pelican_plugins_summary-1.3.1.dist-info/licenses/LICENSE
minchin_pelican_plugins_summary-1.3.1.dist-info/METADATA
minchin_pelican_plugins_summary-1.3.1.dist-info/WHEEL
minchin_pelican_plugins_summary-1.3.1.dist-info/top_level.txt
minchin_pelican_plugins_summary-1.3.1.dist-info/RECORD
