Metadata-Version: 2.4
Name: minchin.pelican.plugins.summary
Version: 1.3.1
Summary: Support Wikilinks when generating Pelican sites
Author-email: William Minchin <w_minchin@hotmail.com>
Maintainer-email: William Minchin <w_minchin@hotmail.com>
License: GNU Affero v3
Project-URL: Bug Tracker, https://github.com/MinchinWeb/minchin.pelican.plugins.summary/issues
Project-URL: Repository, https://github.com/MinchinWeb/minchin.pelican.plugins.summary
Keywords: pelican,plugin
Classifier: Development Status :: 5 - Production/Stable
Classifier: Programming Language :: Python :: 3
Classifier: Environment :: Plugins
Classifier: Framework :: Pelican
Classifier: Framework :: Pelican :: Plugins
Classifier: Intended Audience :: End Users/Desktop
Classifier: Operating System :: OS Independent
Classifier: Topic :: Internet :: WWW/HTTP
Classifier: Topic :: Software Development :: Libraries :: Python Modules
License-File: LICENSE
Requires-Dist: pelican>=4.10
Requires-Dist: packaging
Requires-Dist: minchin.pelican.plugins.autoloader>=1.2.3
Provides-Extra: dev
Requires-Dist: invoke; extra == "dev"
Requires-Dist: twine; extra == "dev"
Requires-Dist: wheel; extra == "dev"
Requires-Dist: minchin.releaser>=0.3.1; extra == "dev"
Dynamic: license-file
